scripts/RISCV_MIPS32.v
module RISCV_FULL(clk1, clk2);

    input clk1, clk2;           //Two phase clock

    reg [31:0] PC, IF_ID_IR, IF_ID_NPC;
    reg [31:0] ID_EX_IR, ID_EX_NPC, ID_EX_A, ID_EX_B, ID_EX_Imm;
    reg [31:0] ID_EX_type, EX_MEM_type, MEM_WB_type;
    reg [31:0] EX_MEM_IR, EX_MEM_ALUout, EX_MEM_B, EX_MEM_cond;
    reg [31:0] MEM_WB_IR, MEM_WB_ALUout, MEM_WB_LMD;
    
    reg [31:0] Reg [31:0];      //Reg bank
    reg [31:0] Mem [0:1023];    //Mem bank

    parameter ADD = 6'b000000, SUB = 6'b000001, AND = 6'b000010, OR = 6'b000011,
              SLT = 6'b000100, MUL = 6'b000101, HLT = 6'b111111, LW = 6'b001000,
              SW = 6'b001001, ADDI = 6'b001010, SUBI = 6'b001011, SLTI = 6'b001100,
              BNEQZ = 6'b001101, BEQZ = 6'b001110;

    parameter RR_ALU = 3'b000, RM_ALU = 3'b001, LOAD = 3'b010, STORE = 3'b011, BRANCH = 3'b100, HALT = 3'b101;

    reg HALTED;             //set after halt instruction
    reg TAKEN_BRANCH;       //required disable instruction after branch


    //------IF------//
    always @(posedge clk1) begin
        if (HALTED == 0) begin
            if (((EX_MEM_IR[31:26] == BEQZ) && (EX_MEM_cond == 1)) || ((EX_MEM_IR[31:26] == BNEQZ) && (EX_MEM_cond == 0))) begin
                //For branch instructions
                IF_ID_IR        <= #2 Mem[EX_MEM_ALUout];
                TAKEN_BRANCH    <= #2 1'b1;
                IF_ID_NPC       <= #2 EX_MEM_ALUout + 1;
                PC              <= #2 EX_MEM_ALUout + 1;
            end
            else begin
                //For normal instructions
                IF_ID_IR    <= #2 Mem[PC];
                IF_ID_NPC   <= #2 PC + 1;
                PC          <= #2 PC + 1;
            end
        end
    end


    //------ID------//
    always @(posedge clk2) begin
        if (HALTED == 0) begin
            if (IF_ID_IR[25:21] == 5'b00000)
                ID_EX_A <= 0;
            else
                ID_EX_A <= #2 Reg[IF_ID_IR[25:21]];     //rs
            
            if (IF_ID_IR[20:16] == 5'b00000)
                ID_EX_B <= 0;
            else
                ID_EX_B <= #2 Reg[IF_ID_IR[20:16]];     //rt
            

            ID_EX_NPC   <= #2 IF_ID_NPC;
            ID_EX_IR    <= #2 IF_ID_IR;
            ID_EX_Imm   <= #2 {{16{IF_ID_IR[15]}}, {IF_ID_IR[15:0]}};     //sign extend

            case (IF_ID_IR[31:26])                      //Grouping
                ADD, SUB, AND, OR, SLT, MUL : ID_EX_type <= #2 RR_ALU;
                ADDI, SUBI, SLTI            : ID_EX_type <= #2 RM_ALU;
                LW                          : ID_EX_type <= #2 LOAD;
                SW                          : ID_EX_type <= #2 STORE;
                BNEQZ, BEQZ                 : ID_EX_type <= #2 BRANCH;
                HLT                         : ID_EX_type <= #2 HALT;
                default                     : ID_EX_type <= #2 HALT; 
            endcase
        end
    end


    //------EX------//
    always @(posedge clk1) begin
        if (HALTED == 0) begin
            EX_MEM_type     <= #2 ID_EX_type;
            EX_MEM_IR       <= #2 ID_EX_IR;
            TAKEN_BRANCH    <= #2 0;

            case (ID_EX_type)
                RR_ALU : begin
                    case (ID_EX_IR[31:26])        //opcode
                        ADD     : EX_MEM_ALUout <= #2 ID_EX_A + ID_EX_B;
                        SUB     : EX_MEM_ALUout <= #2 ID_EX_A - ID_EX_B;
                        AND     : EX_MEM_ALUout <= #2 ID_EX_A & ID_EX_B;
                        OR      : EX_MEM_ALUout <= #2 ID_EX_A | ID_EX_B;
                        SLT     : EX_MEM_ALUout <= #2 ID_EX_A < ID_EX_B;
                        MUL     : EX_MEM_ALUout <= #2 ID_EX_A * ID_EX_B;
                        default : EX_MEM_ALUout <= #2 32'hxxxxxxxx;
                    endcase
                end 

                RM_ALU : begin
                    case (ID_EX_IR[31:26])
                        ADDI    : EX_MEM_ALUout <= #2 ID_EX_A + ID_EX_Imm;
                        SUBI    : EX_MEM_ALUout <= #2 ID_EX_A - ID_EX_Imm;
                        SLTI    : EX_MEM_ALUout <= #2 ID_EX_A < ID_EX_Imm;
                        default : EX_MEM_ALUout <= #2 32'hxxxxxxxx;
                    endcase
                end

                LOAD, STORE : begin
                    EX_MEM_ALUout   <= #2 ID_EX_A + ID_EX_Imm;
                    EX_MEM_B        <= #2 ID_EX_B;
                end

                BRANCH : begin
                    EX_MEM_ALUout   <= #2 ID_EX_NPC + ID_EX_Imm;
                    EX_MEM_cond     <= (ID_EX_A == 0);
                end
            endcase
        end
    end

    //------MEM------//
    always @(posedge clk2) begin
        if (HALTED == 0) begin
            MEM_WB_type     <= EX_MEM_type;
            MEM_WB_IR       <= #2 EX_MEM_IR;

            case (EX_MEM_type)

               RR_ALU, RM_ALU : MEM_WB_ALUout <= #2 EX_MEM_ALUout;

               LOAD           : MEM_WB_LMD    <= #2 Mem[EX_MEM_ALUout];

               STORE          : if(TAKEN_BRANCH == 0)
                                    Mem[EX_MEM_ALUout] <= #2 EX_MEM_B;

            endcase
            
        end
    end
    
    //------WB------//
    always @(posedge clk1) begin
        if(TAKEN_BRANCH == 0)       //Disable write if branch taken
            case (MEM_WB_type)

               RR_ALU : Reg[MEM_WB_IR[15:11]] <= #2 MEM_WB_ALUout;  //rd
               RM_ALU : Reg[MEM_WB_IR[20:16]] <= #2 MEM_WB_ALUout; //rt
               LOAD   : Reg[MEM_WB_IR[20:16]] <= #2 MEM_WB_LMD;       //rt
               HALT   : HALTED                <= #2 1'b1;

            endcase  
    end




endmodule

scripts/RISCV_FULL_tb.v
module RISCV_FULL_tb();
    reg clk1, clk2;
    integer  k;

    RISCV_FULL mips (
        .clk1(clk1), 
        .clk2(clk2)
        );

    initial begin
        clk1 = 0; clk2 = 0;
        repeat(20)
        begin
            #5 clk1 = 1; #5 clk1 = 0;
            #5 clk2 = 1; #5 clk2 = 0;
        end
    end 

/*
    sample input
    ADDI r1, r0, 10
    ADDI r2, r0, 20
    ADDI r3, r0, 25

    ADD r4, r1, r2
    ADD r5, r4, r3
    halt
*/

    initial begin
        for (k = 0; k<31; k=k+1)
            mips.Reg[k] = k;

        mips.Mem[0] = 32'h2801000a;
        mips.Mem[1] = 32'h28020014;
        mips.Mem[2] = 32'h28030019;

        mips.Mem[3] = 32'h0ce77800;     //dummy inst to avoid hazard
        mips.Mem[4] = 32'h0ce77800;     //dummy inst to avoid hazard

        mips.Mem[5] = 32'h00222000;

        mips.Mem[6] = 32'h0ce77800;     //dummy inst to avoid hazard

        mips.Mem[7] = 32'h00832800;
        mips.Mem[8] = 32'hfc000000;

        mips.HALTED = 0;
        mips.PC = 0;
        mips.TAKEN_BRANCH = 0;

        #280
        for(k=0; k<6; k=k+1)
            $display("R%1d - %2d", k, mips.Reg[k]);

    end

    initial begin
        $dumpfile("RISCV.vcd");
        $dumpvars(0);
    end

endmodule

scripts/RISCV.vcd
$date
	Sun Mar 24 13:10:55 2024
$end
$version
	Icarus Verilog
$end
$timescale
	1s
$end
$scope module RISCV_FULL_tb $end
$var reg 1 ! clk1 $end
$var reg 1 " clk2 $end
$var integer 32 # k [31:0] $end
$scope module mips $end
$var wire 1 ! clk1 $end
$var wire 1 " clk2 $end
$var reg 32 $ EX_MEM_ALUout [31:0] $end
$var reg 32 % EX_MEM_B [31:0] $end
$var reg 32 & EX_MEM_IR [31:0] $end
$var reg 32 ' EX_MEM_cond [31:0] $end
$var reg 32 ( EX_MEM_type [31:0] $end
$var reg 1 ) HALTED $end
$var reg 32 * ID_EX_A [31:0] $end
$var reg 32 + ID_EX_B [31:0] $end
$var reg 32 , ID_EX_IR [31:0] $end
$var reg 32 - ID_EX_Imm [31:0] $end
$var reg 32 . ID_EX_NPC [31:0] $end
$var reg 32 / ID_EX_type [31:0] $end
$var reg 32 0 IF_ID_IR [31:0] $end
$var reg 32 1 IF_ID_NPC [31:0] $end
$var reg 32 2 MEM_WB_ALUout [31:0] $end
$var reg 32 3 MEM_WB_IR [31:0] $end
$var reg 32 4 MEM_WB_LMD [31:0] $end
$var reg 32 5 MEM_WB_type [31:0] $end
$var reg 32 6 PC [31:0] $end
$var reg 1 7 TAKEN_BRANCH $end
$upscope $end
$upscope $end
$enddefinitions $end
#0
$dumpvars
07
b0 6
bx 5
bx 4
bx 3
bx 2
bx 1
bx 0
bx /
bx .
bx -
bx ,
bx +
bx *
0)
bx (
bx '
bx &
bx %
bx $
b11111 #
0"
0!
$end
#5
1!
#7
b1 6
b1 1
b101000000000010000000000001010 0
#10
0!
#15
b0 *
1"
#17
b1 /
b1010 -
b101000000000010000000000001010 ,
b1 .
b1 +
#20
0"
#25
1!
#27
b1010 $
b101000000000010000000000001010 &
b1 (
b10 6
b10 1
b101000000000100000000000010100 0
#30
0!
#35
b1 5
1"
#37
b1010 2
b101000000000010000000000001010 3
b10100 -
b101000000000100000000000010100 ,
b10 .
b10 +
#40
0"
#45
1!
#47
b11 6
b11 1
b101000000000110000000000011001 0
b10100 $
b101000000000100000000000010100 &
#50
0!
#55
1"
#57
b11001 -
b101000000000110000000000011001 ,
b11 .
b11 +
b10100 2
b101000000000100000000000010100 3
#60
0"
#65
1!
#67
b11001 $
b101000000000110000000000011001 &
b100 6
b100 1
b1100111001110111100000000000 0
#70
0!
#75
1"
#77
b11001 2
b101000000000110000000000011001 3
b0 /
b111100000000000 -
b1100111001110111100000000000 ,
b100 .
b111 +
b111 *
#80
0"
#85
1!
#87
b101 6
b101 1
b111 $
b1100111001110111100000000000 &
b0 (
#90
0!
#95
b0 5
1"
#97
b101 .
b111 2
b1100111001110111100000000000 3
#100
0"
#105
1!
#107
b110 6
b110 1
b1000100010000000000000 0
#110
0!
#115
1"
#117
b10000000000000 -
b1000100010000000000000 ,
b110 .
b10100 +
b1010 *
#120
0"
#125
1!
#127
b111 6
b111 1
b1100111001110111100000000000 0
b11110 $
b1000100010000000000000 &
#130
0!
#135
1"
#137
b111100000000000 -
b1100111001110111100000000000 ,
b111 .
b111 +
b111 *
b11110 2
b1000100010000000000000 3
#140
0"
#145
1!
#147
b111 $
b1100111001110111100000000000 &
b1000 6
b1000 1
b100000110010100000000000 0
#150
0!
#155
1"
#157
b111 2
b1100111001110111100000000000 3
b10100000000000 -
b100000110010100000000000 ,
b1000 .
b11001 +
b11110 *
#160
0"
#165
1!
#167
b1001 6
b1001 1
b11111100000000000000000000000000 0
b110111 $
b100000110010100000000000 &
#170
0!
#175
b0 +
b0 *
1"
#177
b101 /
b0 -
b11111100000000000000000000000000 ,
b1001 .
b110111 2
b100000110010100000000000 3
#180
0"
#185
1!
#187
b11111100000000000000000000000000 &
b101 (
b1010 6
b1010 1
bx 0
#190
0!
#195
b101 5
1"
#197
b11111100000000000000000000000000 3
bx -
bx ,
b1010 .
bx +
bx *
#200
0"
#205
1!
#207
b1011 6
b1011 1
bx &
1)
#210
0!
#215
1"
#220
0"
#225
1!
#230
0!
#235
1"
#240
0"
#245
1!
#250
0!
#255
1"
#260
0"
#265
1!
#270
0!
#275
1"
#280
0"
b110 #
