src/PC_Adder.v
module PC_Adder (a,b,c);

    input [31:0] a,b;
    output [31:0] c;

    assign c = a + b;
    
endmodule

src/Instruction_Memory.v
//Instruction memory

module Instruction_Memory(rst,A,RD);

  input rst;
  input [31:0]A;
  output [31:0]RD;

  reg [31:0] mem [1023:0];
  
  assign RD = (rst == 1'b0) ? {32{1'b0}} : mem[A[31:2]];

  initial begin
    //$readmemh("memfile.hex",mem);
    mem[0] = 32'hFFC4A303;
  end


/*
  initial begin
    //mem[0] = 32'hFFC4A303;
    //mem[1] = 32'h00832383;
    // mem[0] = 32'h0064A423;
    // mem[1] = 32'h00B62423;
    mem[0] = 32'h0062E233;
    // mem[1] = 32'h00B62423;

  end
*/
endmodule

src/PC.v
module PC_Module(clk,rst,NPC,PC);
    input clk,rst;
    input [31:0] NPC;
    output [31:0] PC;
    reg [31:0] PC;

    always @(posedge clk)
    begin
        if(rst == 1'b0)
            PC <= {32{1'b0}};
        else
            PC <= NPC;
    end
endmodule

src/Mux.v
//2:1 Mux

module Mux (a,b,s,c);

    input [31:0]a,b;
    input s;
    output [31:0]c;

    assign c = (~s) ? a : b ;
    
endmodule

src/Fetch_cycle.v
`include "Mux.v"
`include "PC_Adder.v"
`include "PC.v"
`include "Instruction_Memory.v"

module IF_cycle(clk, rst, EX_MEM_ALUout, EX_MEM_Cond, NPC, IR);

    input clk, rst;
    input EX_MEM_Cond;
    input [31:0] EX_MEM_ALUout;
    output [31:0] NPC, IR;

    //intermediate wires
    wire [31:0] PC_Plus4, PC_Next, NEW_PC;
    wire [31:0] IF_IR;

    //output registers
    reg [31:0] NPC_reg, IR_reg;



    //Modules
    
    //MUX
    Mux PC_Mux(
            .a(PC_Plus4),
            .b(EX_MEM_ALUout),
            .s(EX_MEM_Cond),
            .c(PC_Next)
            );

    //PC counter
    PC_Module Program_Counter(
                        .clk(clk),
                        .rst(rst),
                        .NPC(PC_Next),
                        .PC(NEW_PC)
                        );

    //Instruction memory
    Instruction_Memory IMEM(
                        .rst(rst),
                        .A(NEW_PC),
                        .RD(IF_IR)
                        );

    //Adder For PC
    PC_Adder PC_adder(
                    .a(NEW_PC),
                    .b(32'h00000004),
                    .c(PC_Plus4)
                    );

    //IF reg logic
    always @(posedge clk or negedge rst)  begin
        if(rst == 1'b0)begin
            NPC_reg <= 32'h00000000;
            IR_reg <= 32'h00000000;
        end
        else begin
            NPC_reg <= PC_Next;
            IR_reg <= IF_IR;
        end
    end

    //Assigning reg to output ports
    assign NPC = (rst == 1'b0) ? 32'h00000000 : NPC_reg;
    assign IR = (rst == 1'b0) ? 32'h00000000 : IR_reg;


    
endmodule

src/Fetch_cycle_tb.v
module IF_tb();

    reg clk = 1, rst, EX_MEM_Cond;
    reg [31:0] EX_MEM_ALUout;

    wire [31:0] NPC, IR;

    //DUT
    IF_cycle idut(
        .clk(clk), 
        .rst(rst), 
        .EX_MEM_ALUout(EX_MEM_ALUout), 
        .EX_MEM_Cond(EX_MEM_Cond), 
        .NPC(NPC), 
        .IR(IR)
        );

    //clock cycle
    always begin
        clk = ~clk;
        #50;
    end

    initial begin
        rst <= 1'b0;
        #200;
        rst <= 1'b1;
        EX_MEM_Cond <= 1'b0;
        EX_MEM_ALUout <= 32'h00000000;
        #500;
        $finish;
    end

    initial begin
        $dumpfile("dump.vcd");
        $dumpvars(0);
    end

    
endmodule

src/dump.vcd
$date
	Fri Mar  8 15:43:40 2024
$end
$version
	Icarus Verilog
$end
$timescale
	1s
$end
$scope module IF_tb $end
$var wire 32 ! NPC [31:0] $end
$var wire 32 " IR [31:0] $end
$var reg 32 # EX_MEM_ALUout [31:0] $end
$var reg 1 $ EX_MEM_Cond $end
$var reg 1 % clk $end
$var reg 1 & rst $end
$scope module idut $end
$var wire 32 ' EX_MEM_ALUout [31:0] $end
$var wire 1 $ EX_MEM_Cond $end
$var wire 1 % clk $end
$var wire 1 & rst $end
$var wire 32 ( PC_Plus4 [31:0] $end
$var wire 32 ) PC_Next [31:0] $end
$var wire 32 * NPC [31:0] $end
$var wire 32 + NEW_PC [31:0] $end
$var wire 32 , IR [31:0] $end
$var wire 32 - IF_IR [31:0] $end
$var reg 32 . IR_reg [31:0] $end
$var reg 32 / NPC_reg [31:0] $end
$scope module IMEM $end
$var wire 1 & rst $end
$var wire 32 0 RD [31:0] $end
$var wire 32 1 A [31:0] $end
$upscope $end
$scope module PC_Mux $end
$var wire 32 2 b [31:0] $end
$var wire 1 $ s $end
$var wire 32 3 c [31:0] $end
$var wire 32 4 a [31:0] $end
$upscope $end
$scope module PC_adder $end
$var wire 32 5 b [31:0] $end
$var wire 32 6 c [31:0] $end
$var wire 32 7 a [31:0] $end
$upscope $end
$scope module Program_Counter $end
$var wire 32 8 NPC [31:0] $end
$var wire 1 % clk $end
$var wire 1 & rst $end
$var reg 32 9 PC [31:0] $end
$upscope $end
$upscope $end
$upscope $end
$enddefinitions $end
#0
$dumpvars
bx 9
bx 8
bx 7
bx 6
b100 5
bx 4
bx 3
bx 2
bx 1
b0 0
b0 /
b0 .
b0 -
b0 ,
bx +
b0 *
bx )
bx (
bx '
0&
0%
x$
bx #
b0 "
b0 !
$end
#50
b100 (
b100 4
b100 6
b0 +
b0 1
b0 7
b0 9
1%
#100
0%
#150
1%
#200
b11111111110001001010001100000011 -
b11111111110001001010001100000011 0
b100 )
b100 3
b100 8
b0 #
b0 '
b0 2
0$
1&
0%
#250
bx -
bx 0
b1000 )
b1000 3
b1000 8
b11111111110001001010001100000011 "
b11111111110001001010001100000011 ,
b100 !
b100 *
b1000 (
b1000 4
b1000 6
b100 +
b100 1
b100 7
b100 9
b11111111110001001010001100000011 .
b100 /
1%
#300
0%
#350
b1100 )
b1100 3
b1100 8
bx "
bx ,
b1000 !
b1000 *
b1100 (
b1100 4
b1100 6
b1000 +
b1000 1
b1000 7
b1000 9
bx .
b1000 /
1%
#400
0%
#450
b10000 )
b10000 3
b10000 8
b1100 !
b1100 *
b10000 (
b10000 4
b10000 6
b1100 +
b1100 1
b1100 7
b1100 9
b1100 /
1%
#500
0%
#550
b10100 )
b10100 3
b10100 8
b10000 !
b10000 *
b10100 (
b10100 4
b10100 6
b10000 +
b10000 1
b10000 7
b10000 9
b10000 /
1%
#600
0%
#650
b11000 )
b11000 3
b11000 8
b10100 !
b10100 *
b11000 (
b11000 4
b11000 6
b10100 +
b10100 1
b10100 7
b10100 9
b10100 /
1%
